{"version":"1","myst":"1.6.1","references":[{"kind":"page","data":"/content/index.json","url":"/"},{"identifier":"about-this-collection","kind":"heading","data":"/content/index.json","url":"/","implicit":true},{"identifier":"browse-the-prayers","kind":"heading","data":"/content/index.json","url":"/","implicit":true},{"kind":"page","data":"/content/prayers.json","url":"/prayers"},{"identifier":"a-complete-map-of-moments-for-prayer","kind":"heading","data":"/content/prayers.json","url":"/prayers","implicit":true},{"identifier":"i-the-rhythms-of-the-academic-year","kind":"heading","data":"/content/prayers.json","url":"/prayers","implicit":true},{"identifier":"beginnings","kind":"heading","data":"/content/prayers.json","url":"/prayers","implicit":true},{"identifier":"middles","kind":"heading","data":"/content/prayers.json","url":"/prayers","implicit":true},{"identifier":"endings","kind":"heading","data":"/content/prayers.json","url":"/prayers","implicit":true},{"identifier":"transitions","kind":"heading","data":"/content/prayers.json","url":"/prayers","implicit":true},{"identifier":"ii-the-work-of-learning","kind":"heading","data":"/content/prayers.json","url":"/prayers","implicit":true},{"identifier":"intellectual-struggle","kind":"heading","data":"/content/prayers.json","url":"/prayers","implicit":true},{"identifier":"breakthrough-moments","kind":"heading","data":"/content/prayers.json","url":"/prayers","implicit":true},{"identifier":"daily-work","kind":"heading","data":"/content/prayers.json","url":"/prayers","implicit":true},{"identifier":"assessment","kind":"heading","data":"/content/prayers.json","url":"/prayers","implicit":true},{"identifier":"iii-the-work-of-teaching","kind":"heading","data":"/content/prayers.json","url":"/prayers","implicit":true},{"identifier":"preparation","kind":"heading","data":"/content/prayers.json","url":"/prayers","implicit":true},{"identifier":"in-the-classroom","kind":"heading","data":"/content/prayers.json","url":"/prayers","implicit":true},{"identifier":"one-on-one","kind":"heading","data":"/content/prayers.json","url":"/prayers","implicit":true},{"identifier":"assessment-feedback","kind":"heading","data":"/content/prayers.json","url":"/prayers","implicit":true},{"identifier":"professional-life","kind":"heading","data":"/content/prayers.json","url":"/prayers","implicit":true},{"identifier":"iv-collaboration-community","kind":"heading","data":"/content/prayers.json","url":"/prayers","implicit":true},{"identifier":"working-together","kind":"heading","data":"/content/prayers.json","url":"/prayers","implicit":true},{"identifier":"academic-community","kind":"heading","data":"/content/prayers.json","url":"/prayers","implicit":true},{"identifier":"mentorship","kind":"heading","data":"/content/prayers.json","url":"/prayers","implicit":true},{"identifier":"v-the-practice-of-programming","kind":"heading","data":"/content/prayers.json","url":"/prayers","implicit":true},{"identifier":"creation","kind":"heading","data":"/content/prayers.json","url":"/prayers","implicit":true},{"identifier":"debugging-problem-solving","kind":"heading","data":"/content/prayers.json","url":"/prayers","implicit":true},{"identifier":"testing","kind":"heading","data":"/content/prayers.json","url":"/prayers","implicit":true},{"identifier":"deployment-maintenance","kind":"heading","data":"/content/prayers.json","url":"/prayers","implicit":true},{"identifier":"vi-moments-of-struggle-doubt","kind":"heading","data":"/content/prayers.json","url":"/prayers","implicit":true},{"identifier":"personal-challenges","kind":"heading","data":"/content/prayers.json","url":"/prayers","implicit":true},{"identifier":"failure-setback","kind":"heading","data":"/content/prayers.json","url":"/prayers","implicit":true},{"identifier":"ethical-struggles","kind":"heading","data":"/content/prayers.json","url":"/prayers","implicit":true},{"identifier":"vii-ethical-vocational-formation","kind":"heading","data":"/content/prayers.json","url":"/prayers","implicit":true},{"identifier":"wisdom-discernment","kind":"heading","data":"/content/prayers.json","url":"/prayers","implicit":true},{"identifier":"vocation-calling","kind":"heading","data":"/content/prayers.json","url":"/prayers","implicit":true},{"identifier":"character-formation","kind":"heading","data":"/content/prayers.json","url":"/prayers","implicit":true},{"identifier":"viii-specific-cs-domains-concepts","kind":"heading","data":"/content/prayers.json","url":"/prayers","implicit":true},{"identifier":"core-areas","kind":"heading","data":"/content/prayers.json","url":"/prayers","implicit":true},{"identifier":"specialized-fields","kind":"heading","data":"/content/prayers.json","url":"/prayers","implicit":true},{"identifier":"mathematical-foundations","kind":"heading","data":"/content/prayers.json","url":"/prayers","implicit":true},{"identifier":"ix-technology-tools","kind":"heading","data":"/content/prayers.json","url":"/prayers","implicit":true},{"identifier":"x-seasons-daily-rhythms","kind":"heading","data":"/content/prayers.json","url":"/prayers","implicit":true},{"identifier":"daily-moments","kind":"heading","data":"/content/prayers.json","url":"/prayers","implicit":true},{"identifier":"weekly-rhythms","kind":"heading","data":"/content/prayers.json","url":"/prayers","implicit":true},{"identifier":"seasonal-moments","kind":"heading","data":"/content/prayers.json","url":"/prayers","implicit":true},{"identifier":"xi-relationships-humanity","kind":"heading","data":"/content/prayers.json","url":"/prayers","implicit":true},{"identifier":"with-students","kind":"heading","data":"/content/prayers.json","url":"/prayers","implicit":true},{"identifier":"with-professors","kind":"heading","data":"/content/prayers.json","url":"/prayers","implicit":true},{"identifier":"with-peers","kind":"heading","data":"/content/prayers.json","url":"/prayers","implicit":true},{"identifier":"with-family-friends","kind":"heading","data":"/content/prayers.json","url":"/prayers","implicit":true},{"identifier":"xii-the-life-of-the-mind","kind":"heading","data":"/content/prayers.json","url":"/prayers","implicit":true},{"identifier":"wonder-beauty","kind":"heading","data":"/content/prayers.json","url":"/prayers","implicit":true},{"identifier":"limits-mystery","kind":"heading","data":"/content/prayers.json","url":"/prayers","implicit":true},{"identifier":"integration","kind":"heading","data":"/content/prayers.json","url":"/prayers","implicit":true},{"identifier":"xiii-special-occasions","kind":"heading","data":"/content/prayers.json","url":"/prayers","implicit":true},{"identifier":"celebrations","kind":"heading","data":"/content/prayers.json","url":"/prayers","implicit":true},{"identifier":"commemorations","kind":"heading","data":"/content/prayers.json","url":"/prayers","implicit":true},{"identifier":"lament","kind":"heading","data":"/content/prayers.json","url":"/prayers","implicit":true},{"identifier":"contribute","kind":"heading","data":"/content/prayers.json","url":"/prayers","implicit":true},{"kind":"page","data":"/content/readme.json","url":"/readme"},{"identifier":"about","kind":"heading","data":"/content/readme.json","url":"/readme","implicit":true},{"identifier":"structure","kind":"heading","data":"/content/readme.json","url":"/readme","implicit":true},{"identifier":"getting-started","kind":"heading","data":"/content/readme.json","url":"/readme","implicit":true},{"identifier":"prerequisites","kind":"heading","data":"/content/readme.json","url":"/readme","implicit":true},{"identifier":"installation","kind":"heading","data":"/content/readme.json","url":"/readme","implicit":true},{"identifier":"development","kind":"heading","data":"/content/readme.json","url":"/readme","implicit":true},{"identifier":"building","kind":"heading","data":"/content/readme.json","url":"/readme","implicit":true},{"identifier":"contributing","kind":"heading","data":"/content/readme.json","url":"/readme","implicit":true},{"identifier":"adding-a-new-prayer","kind":"heading","data":"/content/readme.json","url":"/readme","implicit":true},{"identifier":"prayer-writing-guidelines","kind":"heading","data":"/content/readme.json","url":"/readme","implicit":true},{"identifier":"project-structure","kind":"heading","data":"/content/readme.json","url":"/readme","implicit":true},{"identifier":"license","kind":"heading","data":"/content/readme.json","url":"/readme","implicit":true},{"identifier":"acknowledgments","kind":"heading","data":"/content/readme.json","url":"/readme","implicit":true},{"kind":"page","data":"/content/index-1.json","url":"/index-1"},{"identifier":"beginnings","kind":"heading","data":"/content/index-1.json","url":"/index-1","implicit":true},{"identifier":"middles","kind":"heading","data":"/content/index-1.json","url":"/index-1","implicit":true},{"identifier":"endings","kind":"heading","data":"/content/index-1.json","url":"/index-1","implicit":true},{"identifier":"transitions","kind":"heading","data":"/content/index-1.json","url":"/index-1","implicit":true},{"kind":"page","data":"/content/index-2.json","url":"/index-2"},{"kind":"page","data":"/content/capstone-project.json","url":"/capstone-project"},{"kind":"page","data":"/content/first-day-professor.json","url":"/first-day-professor"},{"kind":"page","data":"/content/first-day-student.json","url":"/first-day-student"},{"kind":"page","data":"/content/first-faculty-position.json","url":"/first-faculty-position"},{"kind":"page","data":"/content/graduate-studies.json","url":"/graduate-studies"},{"kind":"page","data":"/content/new-course.json","url":"/new-course"},{"kind":"page","data":"/content/sabbatical.json","url":"/sabbatical"},{"kind":"page","data":"/content/index-3.json","url":"/index-3"},{"kind":"page","data":"/content/end-of-year.json","url":"/end-of-year"},{"kind":"page","data":"/content/final-exam-week-professors.json","url":"/final-exam-week-professors"},{"kind":"page","data":"/content/final-exam-week-students.json","url":"/final-exam-week-students"},{"kind":"page","data":"/content/graduation-professors.json","url":"/graduation-professors"},{"kind":"page","data":"/content/graduation-students.json","url":"/graduation-students"},{"kind":"page","data":"/content/last-class.json","url":"/last-class"},{"kind":"page","data":"/content/submitting-grades.json","url":"/submitting-grades"},{"kind":"page","data":"/content/index-4.json","url":"/index-4"},{"kind":"page","data":"/content/before-spring-break.json","url":"/before-spring-break"},{"kind":"page","data":"/content/challenging-unit.json","url":"/challenging-unit"},{"kind":"page","data":"/content/endless-semester.json","url":"/endless-semester"},{"kind":"page","data":"/content/midterm-season.json","url":"/midterm-season"},{"kind":"page","data":"/content/the-grind.json","url":"/the-grind"},{"kind":"page","data":"/content/index-5.json","url":"/index-5"},{"kind":"page","data":"/content/academia-to-industry.json","url":"/academia-to-industry"},{"kind":"page","data":"/content/choosing-cs-major.json","url":"/choosing-cs-major"},{"kind":"page","data":"/content/declaring-minor.json","url":"/declaring-minor"},{"kind":"page","data":"/content/industry-to-academia.json","url":"/industry-to-academia"},{"kind":"page","data":"/content/retirement.json","url":"/retirement"},{"kind":"page","data":"/content/student-to-professional.json","url":"/student-to-professional"},{"kind":"page","data":"/content/summer-between-years.json","url":"/summer-between-years"},{"kind":"page","data":"/content/switching-to-cs.json","url":"/switching-to-cs"},{"kind":"page","data":"/content/undergrad-to-grad.json","url":"/undergrad-to-grad"},{"kind":"page","data":"/content/index-6.json","url":"/index-6"},{"identifier":"academic-community","kind":"heading","data":"/content/index-6.json","url":"/index-6","implicit":true},{"identifier":"mentorship","kind":"heading","data":"/content/index-6.json","url":"/index-6","implicit":true},{"identifier":"working-together","kind":"heading","data":"/content/index-6.json","url":"/index-6","implicit":true},{"kind":"page","data":"/content/index-7.json","url":"/index-7"},{"kind":"page","data":"/content/colleague-leaves.json","url":"/colleague-leaves"},{"kind":"page","data":"/content/competitive-community.json","url":"/competitive-community"},{"kind":"page","data":"/content/cs-conference.json","url":"/cs-conference"},{"kind":"page","data":"/content/department-meeting.json","url":"/department-meeting"},{"kind":"page","data":"/content/faculty-hiring.json","url":"/faculty-hiring"},{"kind":"page","data":"/content/grace-hopper.json","url":"/grace-hopper"},{"kind":"page","data":"/content/hackathon.json","url":"/hackathon"},{"kind":"page","data":"/content/welcoming-colleague.json","url":"/welcoming-colleague"},{"kind":"page","data":"/content/index-8.json","url":"/index-8"},{"kind":"page","data":"/content/assigned-advisor.json","url":"/assigned-advisor"},{"kind":"page","data":"/content/difficult-mentoring.json","url":"/difficult-mentoring"},{"kind":"page","data":"/content/goodbye-to-advisee.json","url":"/goodbye-to-advisee"},{"kind":"page","data":"/content/mentee-surpasses.json","url":"/mentee-surpasses"},{"kind":"page","data":"/content/mentoring-clicks.json","url":"/mentoring-clicks"},{"kind":"page","data":"/content/taking-advisee.json","url":"/taking-advisee"},{"kind":"page","data":"/content/index-9.json","url":"/index-9"},{"kind":"page","data":"/content/beginning-group-project.json","url":"/beginning-group-project"},{"kind":"page","data":"/content/first-open-source.json","url":"/first-open-source"},{"kind":"page","data":"/content/giving-code-review.json","url":"/giving-code-review"},{"kind":"page","data":"/content/group-conflict.json","url":"/group-conflict"},{"kind":"page","data":"/content/pair-programming.json","url":"/pair-programming"},{"kind":"page","data":"/content/receiving-code-review.json","url":"/receiving-code-review"},{"kind":"page","data":"/content/teammate-not-contributing.json","url":"/teammate-not-contributing"},{"identifier":"when-a-teammate-isnt-contributing","kind":"heading","data":"/content/teammate-not-contributing.json","url":"/teammate-not-contributing","implicit":true},{"kind":"page","data":"/content/you-not-contributing.json","url":"/you-not-contributing"},{"identifier":"when-youre-not-pulling-your-weight","kind":"heading","data":"/content/you-not-contributing.json","url":"/you-not-contributing","implicit":true},{"kind":"page","data":"/content/index-10.json","url":"/index-10"},{"identifier":"core-areas","kind":"heading","data":"/content/index-10.json","url":"/index-10","implicit":true},{"identifier":"mathematical-foundations","kind":"heading","data":"/content/index-10.json","url":"/index-10","implicit":true},{"identifier":"specialized-fields","kind":"heading","data":"/content/index-10.json","url":"/index-10","implicit":true},{"kind":"page","data":"/content/index-11.json","url":"/index-11"},{"kind":"page","data":"/content/algorithms.json","url":"/algorithms"},{"kind":"page","data":"/content/compilers.json","url":"/compilers"},{"kind":"page","data":"/content/computer-architecture.json","url":"/computer-architecture"},{"kind":"page","data":"/content/database-design.json","url":"/database-design"},{"kind":"page","data":"/content/data-structures.json","url":"/data-structures"},{"kind":"page","data":"/content/networks.json","url":"/networks"},{"kind":"page","data":"/content/operating-systems.json","url":"/operating-systems"},{"kind":"page","data":"/content/theory-of-computation.json","url":"/theory-of-computation"},{"kind":"page","data":"/content/index-12.json","url":"/index-12"},{"kind":"page","data":"/content/cryptography.json","url":"/cryptography"},{"kind":"page","data":"/content/discrete-math.json","url":"/discrete-math"},{"kind":"page","data":"/content/formal-methods.json","url":"/formal-methods"},{"kind":"page","data":"/content/graph-theory.json","url":"/graph-theory"},{"kind":"page","data":"/content/linear-algebra.json","url":"/linear-algebra"},{"kind":"page","data":"/content/probability-statistics.json","url":"/probability-statistics"},{"kind":"page","data":"/content/index-13.json","url":"/index-13"},{"kind":"page","data":"/content/beginning-ai-ml.json","url":"/beginning-ai-ml"},{"kind":"page","data":"/content/computer-graphics.json","url":"/computer-graphics"},{"kind":"page","data":"/content/cybersecurity.json","url":"/cybersecurity"},{"kind":"page","data":"/content/embedded-systems.json","url":"/embedded-systems"},{"kind":"page","data":"/content/first-neural-network.json","url":"/first-neural-network"},{"kind":"page","data":"/content/hci.json","url":"/hci"},{"kind":"page","data":"/content/large-language-models.json","url":"/large-language-models"},{"kind":"page","data":"/content/software-engineering.json","url":"/software-engineering"},{"kind":"page","data":"/content/index-14.json","url":"/index-14"},{"identifier":"character-formation","kind":"heading","data":"/content/index-14.json","url":"/index-14","implicit":true},{"identifier":"vocation-calling","kind":"heading","data":"/content/index-14.json","url":"/index-14","implicit":true},{"identifier":"wisdom-discernment","kind":"heading","data":"/content/index-14.json","url":"/index-14","implicit":true},{"kind":"page","data":"/content/index-15.json","url":"/index-15"},{"kind":"page","data":"/content/humbled-by-unknowing.json","url":"/humbled-by-unknowing"},{"identifier":"when-humbled-by-what-you-dont-know","kind":"heading","data":"/content/humbled-by-unknowing.json","url":"/humbled-by-unknowing","implicit":true},{"kind":"page","data":"/content/humility-in-collaboration.json","url":"/humility-in-collaboration"},{"kind":"page","data":"/content/learning-from-mistakes.json","url":"/learning-from-mistakes"},{"kind":"page","data":"/content/patience-through-debugging.json","url":"/patience-through-debugging"},{"kind":"page","data":"/content/perseverance.json","url":"/perseverance"},{"kind":"page","data":"/content/receiving-criticism.json","url":"/receiving-criticism"},{"kind":"page","data":"/content/index-16.json","url":"/index-16"},{"kind":"page","data":"/content/choosing-specialization.json","url":"/choosing-specialization"},{"kind":"page","data":"/content/competing-job-offers.json","url":"/competing-job-offers"},{"kind":"page","data":"/content/discerning-cs.json","url":"/discerning-cs"},{"kind":"page","data":"/content/industry-or-academia.json","url":"/industry-or-academia"},{"kind":"page","data":"/content/is-this-calling.json","url":"/is-this-calling"},{"kind":"page","data":"/content/money-or-meaning.json","url":"/money-or-meaning"},{"kind":"page","data":"/content/skills-serve-others.json","url":"/skills-serve-others"},{"kind":"page","data":"/content/index-17.json","url":"/index-17"},{"kind":"page","data":"/content/accessibility.json","url":"/accessibility"},{"kind":"page","data":"/content/algorithmic-bias.json","url":"/algorithmic-bias"},{"kind":"page","data":"/content/architectural-decisions.json","url":"/architectural-decisions"},{"kind":"page","data":"/content/data-privacy.json","url":"/data-privacy"},{"kind":"page","data":"/content/deploying-ai.json","url":"/deploying-ai"},{"kind":"page","data":"/content/environmental-impact.json","url":"/environmental-impact"},{"kind":"page","data":"/content/profit-vs-ethics.json","url":"/profit-vs-ethics"},{"kind":"page","data":"/content/vulnerable-populations.json","url":"/vulnerable-populations"},{"kind":"page","data":"/content/index-18.json","url":"/index-18"},{"identifier":"intellectual-struggle","kind":"heading","data":"/content/index-18.json","url":"/index-18","implicit":true},{"identifier":"breakthrough-moments","kind":"heading","data":"/content/index-18.json","url":"/index-18","implicit":true},{"identifier":"daily-work","kind":"heading","data":"/content/index-18.json","url":"/index-18","implicit":true},{"identifier":"assessment","kind":"heading","data":"/content/index-18.json","url":"/index-18","implicit":true},{"kind":"page","data":"/content/index-19.json","url":"/index-19"},{"kind":"page","data":"/content/before-exam.json","url":"/before-exam"},{"kind":"page","data":"/content/code-review.json","url":"/code-review"},{"kind":"page","data":"/content/disappointing-grade.json","url":"/disappointing-grade"},{"kind":"page","data":"/content/during-exam.json","url":"/during-exam"},{"kind":"page","data":"/content/encouraging-grade.json","url":"/encouraging-grade"},{"kind":"page","data":"/content/technical-interview.json","url":"/technical-interview"},{"kind":"page","data":"/content/waiting-for-grades.json","url":"/waiting-for-grades"},{"kind":"page","data":"/content/index-20.json","url":"/index-20"},{"kind":"page","data":"/content/completing-challenge.json","url":"/completing-challenge"},{"kind":"page","data":"/content/first-compile-and-run.json","url":"/first-compile-and-run"},{"kind":"page","data":"/content/solving-beyond-you.json","url":"/solving-beyond-you"},{"kind":"page","data":"/content/understanding-dawns.json","url":"/understanding-dawns"},{"kind":"page","data":"/content/unexpected-connection.json","url":"/unexpected-connection"},{"kind":"page","data":"/content/why-it-works.json","url":"/why-it-works"},{"kind":"page","data":"/content/index-21.json","url":"/index-21"},{"kind":"page","data":"/content/asking-question.json","url":"/asking-question"},{"kind":"page","data":"/content/late-night-coding.json","url":"/late-night-coding"},{"kind":"page","data":"/content/office-hours.json","url":"/office-hours"},{"kind":"page","data":"/content/opening-laptop.json","url":"/opening-laptop"},{"kind":"page","data":"/content/reading-documentation.json","url":"/reading-documentation"},{"kind":"page","data":"/content/reviewing-notes.json","url":"/reviewing-notes"},{"kind":"page","data":"/content/study-group.json","url":"/study-group"},{"kind":"page","data":"/content/index-22.json","url":"/index-22"},{"kind":"page","data":"/content/big-o-notation.json","url":"/big-o-notation"},{"kind":"page","data":"/content/concept-wont-click.json","url":"/concept-wont-click"},{"identifier":"when-a-concept-wont-click","kind":"heading","data":"/content/concept-wont-click.json","url":"/concept-wont-click","implicit":true},{"kind":"page","data":"/content/dense-textbook.json","url":"/dense-textbook"},{"kind":"page","data":"/content/everyone-else-understands.json","url":"/everyone-else-understands"},{"kind":"page","data":"/content/functional-programming.json","url":"/functional-programming"},{"kind":"page","data":"/content/impossible-problem-set.json","url":"/impossible-problem-set"},{"kind":"page","data":"/content/new-programming-language.json","url":"/new-programming-language"},{"kind":"page","data":"/content/pointers-and-memory.json","url":"/pointers-and-memory"},{"kind":"page","data":"/content/proofs-first-time.json","url":"/proofs-first-time"},{"kind":"page","data":"/content/recursion.json","url":"/recursion"},{"kind":"page","data":"/content/index-23.json","url":"/index-23"},{"identifier":"integration","kind":"heading","data":"/content/index-23.json","url":"/index-23","implicit":true},{"identifier":"limits-mystery","kind":"heading","data":"/content/index-23.json","url":"/index-23","implicit":true},{"identifier":"wonder-beauty","kind":"heading","data":"/content/index-23.json","url":"/index-23","implicit":true},{"kind":"page","data":"/content/index-24.json","url":"/index-24"},{"kind":"page","data":"/content/cs-liberal-arts.json","url":"/cs-liberal-arts"},{"kind":"page","data":"/content/cs-other-disciplines.json","url":"/cs-other-disciplines"},{"kind":"page","data":"/content/faith-and-technology.json","url":"/faith-and-technology"},{"kind":"page","data":"/content/science-humanities.json","url":"/science-humanities"},{"kind":"page","data":"/content/tech-human-flourishing.json","url":"/tech-human-flourishing"},{"kind":"page","data":"/content/index-25.json","url":"/index-25"},{"kind":"page","data":"/content/consciousness-and-ai.json","url":"/consciousness-and-ai"},{"kind":"page","data":"/content/halting-problem.json","url":"/halting-problem"},{"kind":"page","data":"/content/limits-of-computation.json","url":"/limits-of-computation"},{"kind":"page","data":"/content/questions-tech-cant-answer.json","url":"/questions-tech-cant-answer"},{"identifier":"questions-technology-cant-answer","kind":"heading","data":"/content/questions-tech-cant-answer.json","url":"/questions-tech-cant-answer","implicit":true},{"kind":"page","data":"/content/undecidability.json","url":"/undecidability"},{"kind":"page","data":"/content/what-computers-cant-do.json","url":"/what-computers-cant-do"},{"identifier":"understanding-what-computers-cant-do","kind":"heading","data":"/content/what-computers-cant-do.json","url":"/what-computers-cant-do","implicit":true},{"kind":"page","data":"/content/index-26.json","url":"/index-26"},{"kind":"page","data":"/content/artistry-of-design.json","url":"/artistry-of-design"},{"kind":"page","data":"/content/beautiful-algorithm.json","url":"/beautiful-algorithm"},{"kind":"page","data":"/content/complexity-becomes-simple.json","url":"/complexity-becomes-simple"},{"kind":"page","data":"/content/computational-thinking.json","url":"/computational-thinking"},{"kind":"page","data":"/content/elegant-code.json","url":"/elegant-code"},{"kind":"page","data":"/content/mathematics-beneath.json","url":"/mathematics-beneath"},{"kind":"page","data":"/content/index-27.json","url":"/index-27"},{"identifier":"celebrations","kind":"heading","data":"/content/index-27.json","url":"/index-27","implicit":true},{"identifier":"commemorations","kind":"heading","data":"/content/index-27.json","url":"/index-27","implicit":true},{"identifier":"lament","kind":"heading","data":"/content/index-27.json","url":"/index-27","implicit":true},{"kind":"page","data":"/content/index-28.json","url":"/index-28"},{"kind":"page","data":"/content/defending-thesis.json","url":"/defending-thesis"},{"kind":"page","data":"/content/department-celebrations.json","url":"/department-celebrations"},{"kind":"page","data":"/content/first-hello-world.json","url":"/first-hello-world"},{"identifier":"a-students-first-hello-world","kind":"heading","data":"/content/first-hello-world.json","url":"/first-hello-world","implicit":true},{"kind":"page","data":"/content/first-job-offer.json","url":"/first-job-offer"},{"kind":"page","data":"/content/launching-product.json","url":"/launching-product"},{"kind":"page","data":"/content/publishing-first-paper.json","url":"/publishing-first-paper"},{"kind":"page","data":"/content/winning-hackathon.json","url":"/winning-hackathon"},{"kind":"page","data":"/content/index-29.json","url":"/index-29"},{"kind":"page","data":"/content/cs-pioneer-passes.json","url":"/cs-pioneer-passes"},{"kind":"page","data":"/content/history-of-computing.json","url":"/history-of-computing"},{"kind":"page","data":"/content/honoring-those-before.json","url":"/honoring-those-before"},{"kind":"page","data":"/content/key-moments.json","url":"/key-moments"},{"kind":"page","data":"/content/index-30.json","url":"/index-30"},{"kind":"page","data":"/content/ai-ethics-failures.json","url":"/ai-ethics-failures"},{"kind":"page","data":"/content/algorithms-perpetuate-injustice.json","url":"/algorithms-perpetuate-injustice"},{"kind":"page","data":"/content/dark-side-social-media.json","url":"/dark-side-social-media"},{"kind":"page","data":"/content/data-breaches.json","url":"/data-breaches"},{"kind":"page","data":"/content/innovation-outpaces-wisdom.json","url":"/innovation-outpaces-wisdom"},{"kind":"page","data":"/content/techs-role-in-isolation.json","url":"/techs-role-in-isolation"},{"identifier":"technologys-role-in-isolation","kind":"heading","data":"/content/techs-role-in-isolation.json","url":"/techs-role-in-isolation","implicit":true},{"kind":"page","data":"/content/tech-used-for-harm.json","url":"/tech-used-for-harm"},{"kind":"page","data":"/content/index-31.json","url":"/index-31"},{"identifier":"creation","kind":"heading","data":"/content/index-31.json","url":"/index-31","implicit":true},{"identifier":"debugging-problem-solving","kind":"heading","data":"/content/index-31.json","url":"/index-31","implicit":true},{"identifier":"deployment-maintenance","kind":"heading","data":"/content/index-31.json","url":"/index-31","implicit":true},{"identifier":"testing","kind":"heading","data":"/content/index-31.json","url":"/index-31","implicit":true},{"kind":"page","data":"/content/index-32.json","url":"/index-32"},{"kind":"page","data":"/content/building-beautiful.json","url":"/building-beautiful"},{"kind":"page","data":"/content/choosing-tech-stack.json","url":"/choosing-tech-stack"},{"kind":"page","data":"/content/creative-flow.json","url":"/creative-flow"},{"kind":"page","data":"/content/designing-system.json","url":"/designing-system"},{"kind":"page","data":"/content/first-line-of-code.json","url":"/first-line-of-code"},{"kind":"page","data":"/content/starting-new-project.json","url":"/starting-new-project"},{"kind":"page","data":"/content/index-33.json","url":"/index-33"},{"kind":"page","data":"/content/finding-the-bug.json","url":"/finding-the-bug"},{"kind":"page","data":"/content/hours-of-debugging.json","url":"/hours-of-debugging"},{"kind":"page","data":"/content/hunting-bug.json","url":"/hunting-bug"},{"kind":"page","data":"/content/legacy-code.json","url":"/legacy-code"},{"kind":"page","data":"/content/memory-issues.json","url":"/memory-issues"},{"kind":"page","data":"/content/reading-errors.json","url":"/reading-errors"},{"kind":"page","data":"/content/refactoring.json","url":"/refactoring"},{"kind":"page","data":"/content/runtime-error.json","url":"/runtime-error"},{"kind":"page","data":"/content/stack-overflow-error.json","url":"/stack-overflow-error"},{"kind":"page","data":"/content/wont-compile.json","url":"/wont-compile"},{"identifier":"when-the-code-wont-compile","kind":"heading","data":"/content/wont-compile.json","url":"/wont-compile","implicit":true},{"kind":"page","data":"/content/index-34.json","url":"/index-34"},{"kind":"page","data":"/content/deploying-production.json","url":"/deploying-production"},{"kind":"page","data":"/content/deployment-fails.json","url":"/deployment-fails"},{"kind":"page","data":"/content/maintaining-old-code.json","url":"/maintaining-old-code"},{"kind":"page","data":"/content/monitoring-system.json","url":"/monitoring-system"},{"kind":"page","data":"/content/system-failure.json","url":"/system-failure"},{"kind":"page","data":"/content/index-35.json","url":"/index-35"},{"kind":"page","data":"/content/all-tests-pass.json","url":"/all-tests-pass"},{"kind":"page","data":"/content/integration-testing.json","url":"/integration-testing"},{"kind":"page","data":"/content/tests-fail.json","url":"/tests-fail"},{"kind":"page","data":"/content/user-testing.json","url":"/user-testing"},{"kind":"page","data":"/content/writing-tests.json","url":"/writing-tests"},{"kind":"page","data":"/content/index-36.json","url":"/index-36"},{"identifier":"with-family-friends","kind":"heading","data":"/content/index-36.json","url":"/index-36","implicit":true},{"identifier":"with-peers","kind":"heading","data":"/content/index-36.json","url":"/index-36","implicit":true},{"identifier":"with-professors","kind":"heading","data":"/content/index-36.json","url":"/index-36","implicit":true},{"identifier":"with-students","kind":"heading","data":"/content/index-36.json","url":"/index-36","implicit":true},{"kind":"page","data":"/content/index-37.json","url":"/index-37"},{"kind":"page","data":"/content/loved-ones-support.json","url":"/loved-ones-support"},{"kind":"page","data":"/content/missing-family-time.json","url":"/missing-family-time"},{"kind":"page","data":"/content/non-cs-dont-understand.json","url":"/non-cs-dont-understand"},{"identifier":"when-non-cs-people-dont-understand","kind":"heading","data":"/content/non-cs-dont-understand.json","url":"/non-cs-dont-understand","implicit":true},{"kind":"page","data":"/content/trying-to-explain.json","url":"/trying-to-explain"},{"kind":"page","data":"/content/when-they-dont.json","url":"/when-they-dont"},{"identifier":"when-they-dont","kind":"heading","data":"/content/when-they-dont.json","url":"/when-they-dont","implicit":true},{"kind":"page","data":"/content/index-38.json","url":"/index-38"},{"kind":"page","data":"/content/celebrating-others.json","url":"/celebrating-others"},{"identifier":"celebrating-others-success","kind":"heading","data":"/content/celebrating-others.json","url":"/celebrating-others","implicit":true},{"kind":"page","data":"/content/healthy-competition.json","url":"/healthy-competition"},{"kind":"page","data":"/content/making-friends.json","url":"/making-friends"},{"kind":"page","data":"/content/mutual-learning.json","url":"/mutual-learning"},{"kind":"page","data":"/content/professional-jealousy.json","url":"/professional-jealousy"},{"kind":"page","data":"/content/supporting-peer.json","url":"/supporting-peer"},{"kind":"page","data":"/content/index-39.json","url":"/index-39"},{"kind":"page","data":"/content/disappointing-professor.json","url":"/disappointing-professor"},{"kind":"page","data":"/content/extraordinary-care.json","url":"/extraordinary-care"},{"kind":"page","data":"/content/gratitude-for-mentorship.json","url":"/gratitude-for-mentorship"},{"kind":"page","data":"/content/professors-are-human.json","url":"/professors-are-human"},{"kind":"page","data":"/content/index-40.json","url":"/index-40"},{"kind":"page","data":"/content/celebrating-success.json","url":"/celebrating-success"},{"kind":"page","data":"/content/firm-but-loving.json","url":"/firm-but-loving"},{"kind":"page","data":"/content/grieving-with-students.json","url":"/grieving-with-students"},{"kind":"page","data":"/content/mental-health.json","url":"/mental-health"},{"kind":"page","data":"/content/struggling-personally.json","url":"/struggling-personally"},{"kind":"page","data":"/content/student-discovers-calling.json","url":"/student-discovers-calling"},{"kind":"page","data":"/content/index-41.json","url":"/index-41"},{"identifier":"daily-moments","kind":"heading","data":"/content/index-41.json","url":"/index-41","implicit":true},{"identifier":"seasonal-moments","kind":"heading","data":"/content/index-41.json","url":"/index-41","implicit":true},{"identifier":"weekly-rhythms","kind":"heading","data":"/content/index-41.json","url":"/index-41","implicit":true},{"kind":"page","data":"/content/index-42.json","url":"/index-42"},{"kind":"page","data":"/content/afternoon-slump.json","url":"/afternoon-slump"},{"kind":"page","data":"/content/arriving-lab.json","url":"/arriving-lab"},{"kind":"page","data":"/content/closing-laptop.json","url":"/closing-laptop"},{"kind":"page","data":"/content/commute-to-campus.json","url":"/commute-to-campus"},{"kind":"page","data":"/content/late-night-coding-1.json","url":"/late-night-coding-1"},{"kind":"page","data":"/content/morning-coffee.json","url":"/morning-coffee"},{"kind":"page","data":"/content/returning-fresh.json","url":"/returning-fresh"},{"kind":"page","data":"/content/walking-away.json","url":"/walking-away"},{"kind":"page","data":"/content/index-43.json","url":"/index-43"},{"kind":"page","data":"/content/fall-semester-energy.json","url":"/fall-semester-energy"},{"kind":"page","data":"/content/spring-renewal.json","url":"/spring-renewal"},{"kind":"page","data":"/content/summer-research.json","url":"/summer-research"},{"kind":"page","data":"/content/summer-rest.json","url":"/summer-rest"},{"kind":"page","data":"/content/winter-darkness.json","url":"/winter-darkness"},{"kind":"page","data":"/content/index-44.json","url":"/index-44"},{"kind":"page","data":"/content/friday-afternoon.json","url":"/friday-afternoon"},{"kind":"page","data":"/content/monday-morning.json","url":"/monday-morning"},{"kind":"page","data":"/content/wednesday-hump.json","url":"/wednesday-hump"},{"kind":"page","data":"/content/weekend-rest.json","url":"/weekend-rest"},{"kind":"page","data":"/content/weekend-work.json","url":"/weekend-work"},{"kind":"page","data":"/content/index-45.json","url":"/index-45"},{"identifier":"ethical-struggles","kind":"heading","data":"/content/index-45.json","url":"/index-45","implicit":true},{"identifier":"failure-setback","kind":"heading","data":"/content/index-45.json","url":"/index-45","implicit":true},{"identifier":"personal-challenges","kind":"heading","data":"/content/index-45.json","url":"/index-45","implicit":true},{"kind":"page","data":"/content/index-46.json","url":"/index-46"},{"kind":"page","data":"/content/ai-causing-harm.json","url":"/ai-causing-harm"},{"kind":"page","data":"/content/asked-to-build-wrong.json","url":"/asked-to-build-wrong"},{"kind":"page","data":"/content/code-used-unethically.json","url":"/code-used-unethically"},{"kind":"page","data":"/content/innovation-responsibility.json","url":"/innovation-responsibility"},{"kind":"page","data":"/content/pressure-to-compromise.json","url":"/pressure-to-compromise"},{"kind":"page","data":"/content/reporting-dishonesty.json","url":"/reporting-dishonesty"},{"kind":"page","data":"/content/index-47.json","url":"/index-47"},{"kind":"page","data":"/content/costly-mistake.json","url":"/costly-mistake"},{"kind":"page","data":"/content/failing-exam.json","url":"/failing-exam"},{"kind":"page","data":"/content/grad-school-rejection.json","url":"/grad-school-rejection"},{"kind":"page","data":"/content/grant-denial.json","url":"/grant-denial"},{"kind":"page","data":"/content/laid-off.json","url":"/laid-off"},{"kind":"page","data":"/content/no-internship.json","url":"/no-internship"},{"kind":"page","data":"/content/not-getting-tenure.json","url":"/not-getting-tenure"},{"kind":"page","data":"/content/paper-rejection.json","url":"/paper-rejection"},{"kind":"page","data":"/content/project-fails.json","url":"/project-fails"},{"kind":"page","data":"/content/index-48.json","url":"/index-48"},{"kind":"page","data":"/content/burnout.json","url":"/burnout"},{"kind":"page","data":"/content/comparison.json","url":"/comparison"},{"kind":"page","data":"/content/imposter-syndrome.json","url":"/imposter-syndrome"},{"kind":"page","data":"/content/late-nights-exhaustion.json","url":"/late-nights-exhaustion"},{"kind":"page","data":"/content/missing-personal-events.json","url":"/missing-personal-events"},{"kind":"page","data":"/content/not-creative-enough.json","url":"/not-creative-enough"},{"kind":"page","data":"/content/not-technical-enough.json","url":"/not-technical-enough"},{"kind":"page","data":"/content/work-life-balance.json","url":"/work-life-balance"},{"kind":"page","data":"/content/wrong-field.json","url":"/wrong-field"},{"kind":"page","data":"/content/index-49.json","url":"/index-49"},{"identifier":"preparation","kind":"heading","data":"/content/index-49.json","url":"/index-49","implicit":true},{"identifier":"in-the-classroom","kind":"heading","data":"/content/index-49.json","url":"/index-49","implicit":true},{"identifier":"one-on-one","kind":"heading","data":"/content/index-49.json","url":"/index-49","implicit":true},{"identifier":"assessment-feedback","kind":"heading","data":"/content/index-49.json","url":"/index-49","implicit":true},{"identifier":"professional-life","kind":"heading","data":"/content/index-49.json","url":"/index-49","implicit":true},{"kind":"page","data":"/content/index-50.json","url":"/index-50"},{"kind":"page","data":"/content/before-grading.json","url":"/before-grading"},{"kind":"page","data":"/content/calculating-grades.json","url":"/calculating-grades"},{"kind":"page","data":"/content/exceptional-work.json","url":"/exceptional-work"},{"kind":"page","data":"/content/failing-grade.json","url":"/failing-grade"},{"kind":"page","data":"/content/while-grading.json","url":"/while-grading"},{"kind":"page","data":"/content/writing-feedback.json","url":"/writing-feedback"},{"kind":"page","data":"/content/index-51.json","url":"/index-51"},{"kind":"page","data":"/content/before-class-begins.json","url":"/before-class-begins"},{"kind":"page","data":"/content/last-minutes.json","url":"/last-minutes"},{"kind":"page","data":"/content/live-coding.json","url":"/live-coding"},{"kind":"page","data":"/content/question-unknown-answer.json","url":"/question-unknown-answer"},{"identifier":"a-question-you-cant-answer","kind":"heading","data":"/content/question-unknown-answer.json","url":"/question-unknown-answer","implicit":true},{"kind":"page","data":"/content/starting-lecture.json","url":"/starting-lecture"},{"kind":"page","data":"/content/students-checked-out.json","url":"/students-checked-out"},{"kind":"page","data":"/content/students-engaged.json","url":"/students-engaged"},{"kind":"page","data":"/content/students-not-following.json","url":"/students-not-following"},{"identifier":"when-students-arent-following","kind":"heading","data":"/content/students-not-following.json","url":"/students-not-following","implicit":true},{"kind":"page","data":"/content/teaching-twentieth-time.json","url":"/teaching-twentieth-time"},{"kind":"page","data":"/content/index-52.json","url":"/index-52"},{"kind":"page","data":"/content/academic-dishonesty.json","url":"/academic-dishonesty"},{"kind":"page","data":"/content/before-office-hours.json","url":"/before-office-hours"},{"kind":"page","data":"/content/career-advice.json","url":"/career-advice"},{"kind":"page","data":"/content/mentoring-research.json","url":"/mentoring-research"},{"kind":"page","data":"/content/recommendation-letter.json","url":"/recommendation-letter"},{"kind":"page","data":"/content/struggling-student.json","url":"/struggling-student"},{"kind":"page","data":"/content/index-53.json","url":"/index-53"},{"kind":"page","data":"/content/choosing-topics.json","url":"/choosing-topics"},{"kind":"page","data":"/content/creating-assignment.json","url":"/creating-assignment"},{"kind":"page","data":"/content/designing-exam.json","url":"/designing-exam"},{"kind":"page","data":"/content/learning-to-teach.json","url":"/learning-to-teach"},{"kind":"page","data":"/content/planning-new-course.json","url":"/planning-new-course"},{"kind":"page","data":"/content/preparing-lecture.json","url":"/preparing-lecture"},{"kind":"page","data":"/content/updating-materials.json","url":"/updating-materials"},{"kind":"page","data":"/content/writing-syllabus.json","url":"/writing-syllabus"},{"kind":"page","data":"/content/index-54.json","url":"/index-54"},{"kind":"page","data":"/content/applying-for-grants.json","url":"/applying-for-grants"},{"kind":"page","data":"/content/balancing-teaching-research.json","url":"/balancing-teaching-research"},{"kind":"page","data":"/content/faculty-meeting.json","url":"/faculty-meeting"},{"kind":"page","data":"/content/new-research-project.json","url":"/new-research-project"},{"kind":"page","data":"/content/paper-rejection-1.json","url":"/paper-rejection-1"},{"kind":"page","data":"/content/presenting-conference.json","url":"/presenting-conference"},{"kind":"page","data":"/content/research-dead-end.json","url":"/research-dead-end"},{"kind":"page","data":"/content/reviewing-papers.json","url":"/reviewing-papers"},{"identifier":"reviewing-others-papers","kind":"heading","data":"/content/reviewing-papers.json","url":"/reviewing-papers","implicit":true},{"kind":"page","data":"/content/submitting-paper.json","url":"/submitting-paper"},{"kind":"page","data":"/content/tenure-review.json","url":"/tenure-review"},{"kind":"page","data":"/content/index-55.json","url":"/index-55"},{"kind":"page","data":"/content/backup-recovery.json","url":"/backup-recovery"},{"kind":"page","data":"/content/cloud-computing.json","url":"/cloud-computing"},{"kind":"page","data":"/content/command-line.json","url":"/command-line"},{"kind":"page","data":"/content/database-corruption.json","url":"/database-corruption"},{"kind":"page","data":"/content/dev-environment.json","url":"/dev-environment"},{"kind":"page","data":"/content/first-git.json","url":"/first-git"},{"kind":"page","data":"/content/keyboard-shortcuts.json","url":"/keyboard-shortcuts"},{"kind":"page","data":"/content/lost-work.json","url":"/lost-work"},{"kind":"page","data":"/content/servers-down.json","url":"/servers-down"},{"kind":"page","data":"/content/using-ide.json","url":"/using-ide"},{"kind":"page","data":"/content/working-in-terminal.json","url":"/working-in-terminal"}]}