{"version":2,"kind":"Article","sha256":"85a5c73d8e557d3ee6e8760950094e9f13a52dcadfbb5293ae8ed9b935f2d73c","slug":"ai-causing-harm","location":"/prayers/struggle/ethical/ai-causing-harm.md","dependencies":[],"frontmatter":{"title":"Seeing AI/technology cause harm","content_includes_title":false,"authors":[{"nameParsed":{"literal":"CS Prayers Community","given":"CS Prayers","family":"Community"},"name":"CS Prayers Community","id":"contributors-myst-generated-uid-0"}],"github":"https://github.com/csprayers/csprayers.com","keywords":["prayer","computer science","education","faith"],"numbering":{"title":{"offset":2}},"source_url":"https://github.com/csprayers/csprayers.com/blob/main/prayers/struggle/ethical/ai-causing-harm.md","edit_url":"https://github.com/csprayers/csprayers.com/edit/main/prayers/struggle/ethical/ai-causing-harm.md","exports":[{"format":"md","filename":"ai-causing-harm.md","url":"/ai-causing-harm-f12a4daa45e369207a235113d7840c56.md"}]},"mdast":{"type":"root","children":[{"type":"block","children":[{"type":"paragraph","position":{"start":{"line":7,"column":1},"end":{"line":7,"column":1}},"children":[{"type":"emphasis","position":{"start":{"line":7,"column":1},"end":{"line":7,"column":1}},"children":[{"type":"text","value":"When innovation hurts","position":{"start":{"line":7,"column":1},"end":{"line":7,"column":1}},"key":"OJjRn02wm3"}],"key":"KHrix2IYJt"}],"key":"dtc18g4pAc"},{"type":"thematicBreak","position":{"start":{"line":9,"column":1},"end":{"line":9,"column":1}},"key":"GUSHtLxDSR"},{"type":"paragraph","position":{"start":{"line":11,"column":1},"end":{"line":11,"column":1}},"children":[{"type":"strong","position":{"start":{"line":11,"column":1},"end":{"line":11,"column":1}},"children":[{"type":"text","value":"This prayer is waiting to be written.","position":{"start":{"line":11,"column":1},"end":{"line":11,"column":1}},"key":"EhGcaWmEyJ"}],"key":"Bc02SNRtqk"}],"key":"Erf0Qz8t5N"},{"type":"paragraph","position":{"start":{"line":13,"column":1},"end":{"line":13,"column":1}},"children":[{"type":"text","value":"Would you like to contribute? ","position":{"start":{"line":13,"column":1},"end":{"line":13,"column":1}},"key":"Hb0UZ2CSuL"},{"type":"link","url":"https://github.com/yourusername/csprayers.com/edit/main/prayers/struggle/ethical/ai-causing-harm.md","position":{"start":{"line":13,"column":1},"end":{"line":13,"column":1}},"children":[{"type":"text","value":"Submit a pull request","position":{"start":{"line":13,"column":1},"end":{"line":13,"column":1}},"key":"EZykInCfAE"}],"urlSource":"https://github.com/yourusername/csprayers.com/edit/main/prayers/struggle/ethical/ai-causing-harm.md","error":true,"key":"jY9PqUvSD6"},{"type":"text","value":" to add your prayer here.","position":{"start":{"line":13,"column":1},"end":{"line":13,"column":1}},"key":"sjuMqwJBN1"}],"key":"ouIXxrHldL"}],"key":"SFwqy0zd1Z"}],"key":"XWMTxGHn5q"},"references":{"cite":{"order":[],"data":{}}}}