{"version":2,"kind":"Article","sha256":"709de86b7d3893b14281354bb90f3764e5d1c0744c86a810c7215988dbffbc84","slug":"algorithms-perpetuate-injustice","location":"/prayers/occasions/lament/algorithms-perpetuate-injustice.md","dependencies":[],"frontmatter":{"title":"When algorithms perpetuate injustice","content_includes_title":false,"authors":[{"nameParsed":{"literal":"CS Prayers Community","given":"CS Prayers","family":"Community"},"name":"CS Prayers Community","id":"contributors-myst-generated-uid-0"}],"github":"https://github.com/csprayers/csprayers.com","keywords":["prayer","computer science","education","faith"],"numbering":{"title":{"offset":2}},"source_url":"https://github.com/csprayers/csprayers.com/blob/main/prayers/occasions/lament/algorithms-perpetuate-injustice.md","edit_url":"https://github.com/csprayers/csprayers.com/edit/main/prayers/occasions/lament/algorithms-perpetuate-injustice.md","exports":[{"format":"md","filename":"algorithms-perpetuate-injustice.md","url":"/algorithms-perpetuat-c019729a61074da2c9ec11c98832714f.md"}]},"mdast":{"type":"root","children":[{"type":"block","children":[{"type":"paragraph","position":{"start":{"line":7,"column":1},"end":{"line":7,"column":1}},"children":[{"type":"emphasis","position":{"start":{"line":7,"column":1},"end":{"line":7,"column":1}},"children":[{"type":"text","value":"Systemic harm","position":{"start":{"line":7,"column":1},"end":{"line":7,"column":1}},"key":"lM3oVeuBzH"}],"key":"H4hLS2bHYl"}],"key":"G9L2KP1BLx"},{"type":"thematicBreak","position":{"start":{"line":9,"column":1},"end":{"line":9,"column":1}},"key":"bvhPidSVs9"},{"type":"paragraph","position":{"start":{"line":11,"column":1},"end":{"line":11,"column":1}},"children":[{"type":"strong","position":{"start":{"line":11,"column":1},"end":{"line":11,"column":1}},"children":[{"type":"text","value":"This prayer is waiting to be written.","position":{"start":{"line":11,"column":1},"end":{"line":11,"column":1}},"key":"vdonj6cz5e"}],"key":"ckDKPd8M9U"}],"key":"jSLw5I7QLw"},{"type":"paragraph","position":{"start":{"line":13,"column":1},"end":{"line":13,"column":1}},"children":[{"type":"text","value":"Would you like to contribute? ","position":{"start":{"line":13,"column":1},"end":{"line":13,"column":1}},"key":"UXCcrRBuZU"},{"type":"link","url":"https://github.com/yourusername/csprayers.com/edit/main/prayers/occasions/lament/algorithms-perpetuate-injustice.md","position":{"start":{"line":13,"column":1},"end":{"line":13,"column":1}},"children":[{"type":"text","value":"Submit a pull request","position":{"start":{"line":13,"column":1},"end":{"line":13,"column":1}},"key":"twx0GhhJ4v"}],"urlSource":"https://github.com/yourusername/csprayers.com/edit/main/prayers/occasions/lament/algorithms-perpetuate-injustice.md","error":true,"key":"qSTJt1r3uX"},{"type":"text","value":" to add your prayer here.","position":{"start":{"line":13,"column":1},"end":{"line":13,"column":1}},"key":"YoQ5R544vt"}],"key":"G0VSGOEmqC"}],"key":"BSGogvDF9B"}],"key":"SFuWgzBQow"},"references":{"cite":{"order":[],"data":{}}}}