{"version":2,"kind":"Article","sha256":"49ea2397154fca8a611e43e5385a6681714cb6e09ae7a3e870d612eb243aff5b","slug":"choosing-topics","location":"/3-teaching/preparation/choosing-topics.md","dependencies":[],"frontmatter":{"title":"🔴 Choosing which topics to include/exclude","authors":[{"nameParsed":{"literal":"CS Prayers Community","given":"CS Prayers","family":"Community"},"name":"CS Prayers Community","id":"contributors-myst-generated-uid-0"}],"github":"https://github.com/csprayers/csprayers.com","keywords":["prayer","computer science","education","faith"],"numbering":{"title":{"offset":2}},"source_url":"https://github.com/csprayers/csprayers.com/blob/main/3-teaching/preparation/choosing-topics.md","edit_url":"https://github.com/csprayers/csprayers.com/edit/main/3-teaching/preparation/choosing-topics.md","exports":[{"format":"md","filename":"choosing-topics.md","url":"/choosing-topics-1e47caf72c07690fa879a51121b03f03.md"}]},"mdast":{"type":"root","children":[{"type":"block","children":[{"type":"paragraph","position":{"start":{"line":5,"column":1},"end":{"line":5,"column":1}},"children":[{"type":"emphasis","position":{"start":{"line":5,"column":1},"end":{"line":5,"column":1}},"children":[{"type":"text","value":"Making difficult curriculum decisions","position":{"start":{"line":5,"column":1},"end":{"line":5,"column":1}},"key":"GyW6w7H3I0"}],"key":"PVgowSQ98B"}],"key":"qY6KETua0B"},{"type":"thematicBreak","position":{"start":{"line":7,"column":1},"end":{"line":7,"column":1}},"key":"fmUA8qk74B"},{"type":"paragraph","position":{"start":{"line":9,"column":1},"end":{"line":9,"column":1}},"children":[{"type":"strong","position":{"start":{"line":9,"column":1},"end":{"line":9,"column":1}},"children":[{"type":"text","value":"This prayer is waiting to be written.","position":{"start":{"line":9,"column":1},"end":{"line":9,"column":1}},"key":"CSfsi8TibY"}],"key":"U9K4eHBZvo"}],"key":"ymMyVDKHRQ"},{"type":"paragraph","position":{"start":{"line":11,"column":1},"end":{"line":11,"column":1}},"children":[{"type":"text","value":"Would you like to contribute? ","position":{"start":{"line":11,"column":1},"end":{"line":11,"column":1}},"key":"MZwcF0N8gG"},{"type":"link","url":"https://github.com/csprayers/csprayers.com/edit/main/3-teaching/preparation/choosing-topics.md","position":{"start":{"line":11,"column":1},"end":{"line":11,"column":1}},"children":[{"type":"text","value":"Submit a pull request","position":{"start":{"line":11,"column":1},"end":{"line":11,"column":1}},"key":"RmothZ2j1u"}],"urlSource":"https://github.com/csprayers/csprayers.com/edit/main/3-teaching/preparation/choosing-topics.md","error":true,"key":"ZPsRD65zlW"},{"type":"text","value":" to add your prayer here.","position":{"start":{"line":11,"column":1},"end":{"line":11,"column":1}},"key":"x55mLnipsU"}],"key":"M6IANGVnLW"}],"key":"Vh4KMDYRWh"}],"key":"PwiwKylUia"},"references":{"cite":{"order":[],"data":{}}}}