{"version":2,"kind":"Article","sha256":"4c0d9ae8dd53118d1a66e9b68d5f7399d3235847f6fe287aaa95c3f088c5e097","slug":"choosing-cs-major","location":"/1-academic-year/transitions/choosing-cs-major.md","dependencies":[],"frontmatter":{"title":"🔴 Choosing a major in computer science","authors":[{"nameParsed":{"literal":"CS Prayers Community","given":"CS Prayers","family":"Community"},"name":"CS Prayers Community","id":"contributors-myst-generated-uid-0"}],"github":"https://github.com/csprayers/csprayers.com","keywords":["prayer","computer science","education","faith"],"numbering":{"title":{"offset":2}},"source_url":"https://github.com/csprayers/csprayers.com/blob/main/1-academic-year/transitions/choosing-cs-major.md","edit_url":"https://github.com/csprayers/csprayers.com/edit/main/1-academic-year/transitions/choosing-cs-major.md","exports":[{"format":"md","filename":"choosing-cs-major.md","url":"/choosing-cs-major-5997c286d84fc2dce4b0ae0ca954450d.md"}]},"mdast":{"type":"root","children":[{"type":"block","children":[{"type":"paragraph","position":{"start":{"line":5,"column":1},"end":{"line":5,"column":1}},"children":[{"type":"emphasis","position":{"start":{"line":5,"column":1},"end":{"line":5,"column":1}},"children":[{"type":"text","value":"Declaring your major","position":{"start":{"line":5,"column":1},"end":{"line":5,"column":1}},"key":"cuo63nzcux"}],"key":"sBx3AeDSCa"}],"key":"XghibxHOrT"},{"type":"thematicBreak","position":{"start":{"line":7,"column":1},"end":{"line":7,"column":1}},"key":"FiB1f8uTID"},{"type":"paragraph","position":{"start":{"line":9,"column":1},"end":{"line":9,"column":1}},"children":[{"type":"strong","position":{"start":{"line":9,"column":1},"end":{"line":9,"column":1}},"children":[{"type":"text","value":"This prayer is waiting to be written.","position":{"start":{"line":9,"column":1},"end":{"line":9,"column":1}},"key":"af1p1afpWF"}],"key":"fKzmMF6G5c"}],"key":"wZPchH1nye"},{"type":"paragraph","position":{"start":{"line":11,"column":1},"end":{"line":11,"column":1}},"children":[{"type":"text","value":"Would you like to contribute? ","position":{"start":{"line":11,"column":1},"end":{"line":11,"column":1}},"key":"oru4l6acRK"},{"type":"link","url":"https://github.com/csprayers/csprayers.com/edit/main/1-academic-year/transitions/choosing-cs-major.md","position":{"start":{"line":11,"column":1},"end":{"line":11,"column":1}},"children":[{"type":"text","value":"Submit a pull request","position":{"start":{"line":11,"column":1},"end":{"line":11,"column":1}},"key":"vE9PeO8YW9"}],"urlSource":"https://github.com/csprayers/csprayers.com/edit/main/1-academic-year/transitions/choosing-cs-major.md","error":true,"key":"wRHOhfQErR"},{"type":"text","value":" to add your prayer here.","position":{"start":{"line":11,"column":1},"end":{"line":11,"column":1}},"key":"s20fGboOiD"}],"key":"mnduzDSZ1N"}],"key":"PPbVkjeIrD"}],"key":"grvmpnXinJ"},"references":{"cite":{"order":[],"data":{}}}}