{"version":2,"kind":"Article","sha256":"56df0c0924872b4c278a2806e93df34d6d89ac26b0cc6fcb1f0553b0c39e7237","slug":"closing-laptop","location":"/10-rhythms/daily/closing-laptop.md","dependencies":[],"frontmatter":{"title":"🔴 Closing your laptop for the day","authors":[{"nameParsed":{"literal":"CS Prayers Community","given":"CS Prayers","family":"Community"},"name":"CS Prayers Community","id":"contributors-myst-generated-uid-0"}],"github":"https://github.com/csprayers/csprayers.com","keywords":["prayer","computer science","education","faith"],"numbering":{"title":{"offset":2}},"source_url":"https://github.com/csprayers/csprayers.com/blob/main/10-rhythms/daily/closing-laptop.md","edit_url":"https://github.com/csprayers/csprayers.com/edit/main/10-rhythms/daily/closing-laptop.md","exports":[{"format":"md","filename":"closing-laptop.md","url":"/closing-laptop-966248dbefdd719d9550fc8559b446c8.md"}]},"mdast":{"type":"root","children":[{"type":"block","children":[{"type":"paragraph","position":{"start":{"line":5,"column":1},"end":{"line":5,"column":1}},"children":[{"type":"emphasis","position":{"start":{"line":5,"column":1},"end":{"line":5,"column":1}},"children":[{"type":"text","value":"Ending the workday","position":{"start":{"line":5,"column":1},"end":{"line":5,"column":1}},"key":"z7AbLgpxKu"}],"key":"CJvQgDYrGT"}],"key":"gmHsucKrfb"},{"type":"thematicBreak","position":{"start":{"line":7,"column":1},"end":{"line":7,"column":1}},"key":"KwTLp2sxp2"},{"type":"paragraph","position":{"start":{"line":9,"column":1},"end":{"line":9,"column":1}},"children":[{"type":"strong","position":{"start":{"line":9,"column":1},"end":{"line":9,"column":1}},"children":[{"type":"text","value":"This prayer is waiting to be written.","position":{"start":{"line":9,"column":1},"end":{"line":9,"column":1}},"key":"CT6mntQ8lW"}],"key":"Ta5XdmyKd7"}],"key":"GGN5bC8l0t"},{"type":"paragraph","position":{"start":{"line":11,"column":1},"end":{"line":11,"column":1}},"children":[{"type":"text","value":"Would you like to contribute? ","position":{"start":{"line":11,"column":1},"end":{"line":11,"column":1}},"key":"XQ8ogQGMGi"},{"type":"link","url":"https://github.com/csprayers/csprayers.com/edit/main/10-rhythms/daily/closing-laptop.md","position":{"start":{"line":11,"column":1},"end":{"line":11,"column":1}},"children":[{"type":"text","value":"Submit a pull request","position":{"start":{"line":11,"column":1},"end":{"line":11,"column":1}},"key":"Tt4GPQ6WOo"}],"urlSource":"https://github.com/csprayers/csprayers.com/edit/main/10-rhythms/daily/closing-laptop.md","error":true,"key":"CGWuw4t6jY"},{"type":"text","value":" to add your prayer here.","position":{"start":{"line":11,"column":1},"end":{"line":11,"column":1}},"key":"CMFVMrF7nY"}],"key":"VG9WVRei4C"}],"key":"iasjZkmif2"}],"key":"DzpXornsR3"},"references":{"cite":{"order":[],"data":{}}}}