{"version":2,"kind":"Article","sha256":"5981d91c64ce7bdb3126348f5a0b032590573a7f263ea6b1bcd8fb4582b5f54a","slug":"concept-wont-click","location":"/2-learning/intellectual-struggle/concept-wont-click.md","dependencies":[],"frontmatter":{"title":"🔴 When a concept won't \"click\"","authors":[{"nameParsed":{"literal":"CS Prayers Community","given":"CS Prayers","family":"Community"},"name":"CS Prayers Community","id":"contributors-myst-generated-uid-0"}],"github":"https://github.com/csprayers/csprayers.com","keywords":["prayer","computer science","education","faith"],"numbering":{"title":{"offset":2}},"source_url":"https://github.com/csprayers/csprayers.com/blob/main/2-learning/intellectual-struggle/concept-wont-click.md","edit_url":"https://github.com/csprayers/csprayers.com/edit/main/2-learning/intellectual-struggle/concept-wont-click.md","exports":[{"format":"md","filename":"concept-wont-click.md","url":"/concept-wont-click-c1aa1cd36708298a9d353a533b785f5f.md"}]},"mdast":{"type":"root","children":[{"type":"block","children":[{"type":"paragraph","position":{"start":{"line":5,"column":1},"end":{"line":5,"column":1}},"children":[{"type":"emphasis","position":{"start":{"line":5,"column":1},"end":{"line":5,"column":1}},"children":[{"type":"text","value":"In the fog of confusion","position":{"start":{"line":5,"column":1},"end":{"line":5,"column":1}},"key":"RwuiVUf9fd"}],"key":"Ccdz4BlUMw"}],"key":"xZCHIbrOvV"},{"type":"thematicBreak","position":{"start":{"line":7,"column":1},"end":{"line":7,"column":1}},"key":"fPqcgbqML0"},{"type":"paragraph","position":{"start":{"line":9,"column":1},"end":{"line":9,"column":1}},"children":[{"type":"strong","position":{"start":{"line":9,"column":1},"end":{"line":9,"column":1}},"children":[{"type":"text","value":"This prayer is waiting to be written.","position":{"start":{"line":9,"column":1},"end":{"line":9,"column":1}},"key":"tuLnNRKXbQ"}],"key":"uuaWmVdev7"}],"key":"bgXSkWgCPH"},{"type":"paragraph","position":{"start":{"line":11,"column":1},"end":{"line":11,"column":1}},"children":[{"type":"text","value":"Would you like to contribute? ","position":{"start":{"line":11,"column":1},"end":{"line":11,"column":1}},"key":"MJDlQEbI9b"},{"type":"link","url":"https://github.com/yourusername/csprayers.com/edit/main/prayers/learning/intellectual-struggle/concept-wont-click.md","position":{"start":{"line":11,"column":1},"end":{"line":11,"column":1}},"children":[{"type":"text","value":"Submit a pull request","position":{"start":{"line":11,"column":1},"end":{"line":11,"column":1}},"key":"BD7WSZrUVo"}],"urlSource":"https://github.com/yourusername/csprayers.com/edit/main/prayers/learning/intellectual-struggle/concept-wont-click.md","error":true,"key":"oxoID6j1kF"},{"type":"text","value":" to add your prayer here.","position":{"start":{"line":11,"column":1},"end":{"line":11,"column":1}},"key":"u3w0C72bT3"}],"key":"AmAHloDD65"}],"key":"bI8kwdsv5Q"}],"key":"CpybxesnaX"},"references":{"cite":{"order":[],"data":{}}}}