{"version":2,"kind":"Article","sha256":"5834f6184f18ed289efca7152cb5c6f415601b516dab47d6edb1bdc05ae09ebf","slug":"graduation-students","location":"/1-academic-year/endings/graduation-students.md","dependencies":[],"frontmatter":{"title":"🔴 Graduation day (for students)","authors":[{"nameParsed":{"literal":"CS Prayers Community","given":"CS Prayers","family":"Community"},"name":"CS Prayers Community","id":"contributors-myst-generated-uid-0"}],"github":"https://github.com/csprayers/csprayers.com","keywords":["prayer","computer science","education","faith"],"numbering":{"title":{"offset":2}},"source_url":"https://github.com/csprayers/csprayers.com/blob/main/1-academic-year/endings/graduation-students.md","edit_url":"https://github.com/csprayers/csprayers.com/edit/main/1-academic-year/endings/graduation-students.md","exports":[{"format":"md","filename":"graduation-students.md","url":"/graduation-students-8da544139566f3adb85bada4c9f4a27c.md"}]},"mdast":{"type":"root","children":[{"type":"block","children":[{"type":"paragraph","position":{"start":{"line":5,"column":1},"end":{"line":5,"column":1}},"children":[{"type":"emphasis","position":{"start":{"line":5,"column":1},"end":{"line":5,"column":1}},"children":[{"type":"text","value":"At commencement","position":{"start":{"line":5,"column":1},"end":{"line":5,"column":1}},"key":"J7EvJ5AQGK"}],"key":"Yc3PyR6M3N"}],"key":"JKvHadap2i"},{"type":"thematicBreak","position":{"start":{"line":7,"column":1},"end":{"line":7,"column":1}},"key":"QG1QjgHXOr"},{"type":"paragraph","position":{"start":{"line":9,"column":1},"end":{"line":9,"column":1}},"children":[{"type":"strong","position":{"start":{"line":9,"column":1},"end":{"line":9,"column":1}},"children":[{"type":"text","value":"This prayer is waiting to be written.","position":{"start":{"line":9,"column":1},"end":{"line":9,"column":1}},"key":"CJDy2ugf4n"}],"key":"Fu5r9UyESH"}],"key":"Z68xoyMsLx"},{"type":"paragraph","position":{"start":{"line":11,"column":1},"end":{"line":11,"column":1}},"children":[{"type":"text","value":"Would you like to contribute? ","position":{"start":{"line":11,"column":1},"end":{"line":11,"column":1}},"key":"VrNHa9PF9L"},{"type":"link","url":"https://github.com/yourusername/csprayers.com/edit/main/prayers/academic-year/endings/graduation-students.md","position":{"start":{"line":11,"column":1},"end":{"line":11,"column":1}},"children":[{"type":"text","value":"Submit a pull request","position":{"start":{"line":11,"column":1},"end":{"line":11,"column":1}},"key":"bh4otPdTeg"}],"urlSource":"https://github.com/yourusername/csprayers.com/edit/main/prayers/academic-year/endings/graduation-students.md","error":true,"key":"OObDOdMC5h"},{"type":"text","value":" to add your prayer here.","position":{"start":{"line":11,"column":1},"end":{"line":11,"column":1}},"key":"Z5iNJRpw9j"}],"key":"s8b0h1OsND"}],"key":"KqR0x0XjND"}],"key":"xhtXFgriSH"},"references":{"cite":{"order":[],"data":{}}}}