{"version":2,"kind":"Article","sha256":"20888d9f751290b9494ab262543204529e4f2a166faed94e4f10254ba3f6ac59","slug":"index-15","location":"/prayers/formation/character/index.md","dependencies":[],"frontmatter":{"title":"Character Formation","content_includes_title":false,"authors":[{"nameParsed":{"literal":"CS Prayers Community","given":"CS Prayers","family":"Community"},"name":"CS Prayers Community","id":"contributors-myst-generated-uid-0"}],"github":"https://github.com/csprayers/csprayers.com","keywords":["prayer","computer science","education","faith"],"numbering":{"title":{"offset":3}},"exports":[{"format":"md","filename":"index.md","url":"/index-e424629ce1b43afdf71c0c1cb7afb065.md"}]},"mdast":{"type":"root","children":[{"type":"block","children":[{"type":"paragraph","position":{"start":{"line":7,"column":1},"end":{"line":7,"column":1}},"children":[{"type":"text","value":"Prayers for humility, patience, perseverance, and grace","position":{"start":{"line":7,"column":1},"end":{"line":7,"column":1}},"key":"atzcY1eY5H"}],"key":"w2o9jSHAz4"},{"type":"thematicBreak","position":{"start":{"line":9,"column":1},"end":{"line":9,"column":1}},"key":"SNzlnrxTTr"},{"type":"list","ordered":false,"spread":false,"position":{"start":{"line":12,"column":1},"end":{"line":17,"column":1}},"children":[{"type":"listItem","spread":true,"position":{"start":{"line":12,"column":1},"end":{"line":12,"column":1}},"children":[{"type":"paragraph","children":[{"type":"link","url":"/humbled-by-unknowing","position":{"start":{"line":12,"column":1},"end":{"line":12,"column":1}},"children":[{"type":"text","value":"Humbled By Unknowing","position":{"start":{"line":12,"column":1},"end":{"line":12,"column":1}},"key":"YsIcvcPcCr"}],"urlSource":"humbled-by-unknowing.md","dataUrl":"/humbled-by-unknowing.json","internal":true,"protocol":"file","key":"oAanQ9oXqL"}],"key":"mvrEgX0k9t"}],"key":"v2MTB7i1q6"},{"type":"listItem","spread":true,"position":{"start":{"line":13,"column":1},"end":{"line":13,"column":1}},"children":[{"type":"paragraph","children":[{"type":"link","url":"/humility-in-collaboration","position":{"start":{"line":13,"column":1},"end":{"line":13,"column":1}},"children":[{"type":"text","value":"Humility In Collaboration","position":{"start":{"line":13,"column":1},"end":{"line":13,"column":1}},"key":"eKa4Z42IDh"}],"urlSource":"humility-in-collaboration.md","dataUrl":"/humility-in-collaboration.json","internal":true,"protocol":"file","key":"dCshtpPGiU"}],"key":"ZzjhSXolrX"}],"key":"nCeTi2ToiF"},{"type":"listItem","spread":true,"position":{"start":{"line":14,"column":1},"end":{"line":14,"column":1}},"children":[{"type":"paragraph","children":[{"type":"link","url":"/learning-from-mistakes","position":{"start":{"line":14,"column":1},"end":{"line":14,"column":1}},"children":[{"type":"text","value":"Learning From Mistakes","position":{"start":{"line":14,"column":1},"end":{"line":14,"column":1}},"key":"CvhZkNStdx"}],"urlSource":"learning-from-mistakes.md","dataUrl":"/learning-from-mistakes.json","internal":true,"protocol":"file","key":"FrIeGKeihB"}],"key":"nkMzuhNEeL"}],"key":"nXRMeGVUO5"},{"type":"listItem","spread":true,"position":{"start":{"line":15,"column":1},"end":{"line":15,"column":1}},"children":[{"type":"paragraph","children":[{"type":"link","url":"/patience-through-debugging","position":{"start":{"line":15,"column":1},"end":{"line":15,"column":1}},"children":[{"type":"text","value":"Patience Through Debugging","position":{"start":{"line":15,"column":1},"end":{"line":15,"column":1}},"key":"ZtppBP5CcP"}],"urlSource":"patience-through-debugging.md","dataUrl":"/patience-through-debugging.json","internal":true,"protocol":"file","key":"HKsEJNPCuB"}],"key":"Tw5j3kdKRd"}],"key":"lEBqySFcsS"},{"type":"listItem","spread":true,"position":{"start":{"line":16,"column":1},"end":{"line":16,"column":1}},"children":[{"type":"paragraph","children":[{"type":"link","url":"/perseverance","position":{"start":{"line":16,"column":1},"end":{"line":16,"column":1}},"children":[{"type":"text","value":"Perseverance","position":{"start":{"line":16,"column":1},"end":{"line":16,"column":1}},"key":"eEy4Vdm8Px"}],"urlSource":"perseverance.md","dataUrl":"/perseverance.json","internal":true,"protocol":"file","key":"sbNdvsJB8s"}],"key":"MtVdh35IAY"}],"key":"SOjwkO6iwP"},{"type":"listItem","spread":true,"position":{"start":{"line":17,"column":1},"end":{"line":17,"column":1}},"children":[{"type":"paragraph","children":[{"type":"link","url":"/receiving-criticism","position":{"start":{"line":17,"column":1},"end":{"line":17,"column":1}},"children":[{"type":"text","value":"Receiving Criticism","position":{"start":{"line":17,"column":1},"end":{"line":17,"column":1}},"key":"TJkYt1PUkO"}],"urlSource":"receiving-criticism.md","dataUrl":"/receiving-criticism.json","internal":true,"protocol":"file","key":"IMIsYXgi52"}],"key":"n0zNqA43BD"}],"key":"cygUpso5eG"}],"key":"ILNeDKQbiY"}],"key":"Sjx0Ta3yZh"}],"key":"ljURly1jXo"},"references":{"cite":{"order":[],"data":{}}}}