{"version":2,"kind":"Article","sha256":"bd45fc1502c8023661d845d57d3736665d898808785d42476e733354ca4ff53b","slug":"monday-morning","location":"/prayers/rhythms/weekly/monday-morning.md","dependencies":[],"frontmatter":{"title":"Monday Morning","content_includes_title":false,"authors":[{"nameParsed":{"literal":"CS Prayers Community","given":"CS Prayers","family":"Community"},"name":"CS Prayers Community","id":"contributors-myst-generated-uid-0"}],"github":"https://github.com/csprayers/csprayers.com","keywords":["prayer","computer science","education","faith"],"numbering":{"title":{"offset":3}},"exports":[{"format":"md","filename":"monday-morning.md","url":"/monday-morning-175ed3486be5fea2712909db1e800d9d.md"}]},"mdast":{"type":"root","children":[{"type":"block","children":[{"type":"paragraph","position":{"start":{"line":7,"column":1},"end":{"line":7,"column":1}},"children":[{"type":"emphasis","position":{"start":{"line":7,"column":1},"end":{"line":7,"column":1}},"children":[{"type":"text","value":"The week begins","position":{"start":{"line":7,"column":1},"end":{"line":7,"column":1}},"key":"H6oYuKxqQh"}],"key":"iV1IVXk2E6"}],"key":"jY962x6gTQ"},{"type":"thematicBreak","position":{"start":{"line":9,"column":1},"end":{"line":9,"column":1}},"key":"QUZG3gsLq7"},{"type":"paragraph","position":{"start":{"line":11,"column":1},"end":{"line":11,"column":1}},"children":[{"type":"strong","position":{"start":{"line":11,"column":1},"end":{"line":11,"column":1}},"children":[{"type":"text","value":"This prayer is waiting to be written.","position":{"start":{"line":11,"column":1},"end":{"line":11,"column":1}},"key":"szCUF01gEB"}],"key":"GQpNrBv6Nj"}],"key":"v1jjjpHATx"},{"type":"paragraph","position":{"start":{"line":13,"column":1},"end":{"line":13,"column":1}},"children":[{"type":"text","value":"Would you like to contribute? ","position":{"start":{"line":13,"column":1},"end":{"line":13,"column":1}},"key":"C43McNpf7M"},{"type":"link","url":"https://github.com/yourusername/csprayers.com/edit/main/prayers/rhythms/weekly/monday-morning.md","position":{"start":{"line":13,"column":1},"end":{"line":13,"column":1}},"children":[{"type":"text","value":"Submit a pull request","position":{"start":{"line":13,"column":1},"end":{"line":13,"column":1}},"key":"LnJpJP2j1o"}],"urlSource":"https://github.com/yourusername/csprayers.com/edit/main/prayers/rhythms/weekly/monday-morning.md","error":true,"key":"VIA5cOSAPW"},{"type":"text","value":" to add your prayer here.","position":{"start":{"line":13,"column":1},"end":{"line":13,"column":1}},"key":"dBeoSISftL"}],"key":"XfhjRUDbZN"}],"key":"p6MnC5dMap"}],"key":"iPtNOzPf8I"},"references":{"cite":{"order":[],"data":{}}}}