{"version":2,"kind":"Article","sha256":"e51dcc1fc57e3a075407f45c4d0973140e614ce1a986b3952e9913cade8b4cc1","slug":"reporting-dishonesty","location":"/prayers/struggle/ethical/reporting-dishonesty.md","dependencies":[],"frontmatter":{"title":"Reporting Academic Dishonesty","content_includes_title":false,"authors":[{"nameParsed":{"literal":"CS Prayers Community","given":"CS Prayers","family":"Community"},"name":"CS Prayers Community","id":"contributors-myst-generated-uid-0"}],"github":"https://github.com/csprayers/csprayers.com","keywords":["prayer","computer science","education","faith"],"numbering":{"title":{"offset":3}},"exports":[{"format":"md","filename":"reporting-dishonesty.md","url":"/reporting-dishonesty-b73d41abe999fd1c3dfd0172cfa2eeea.md"}]},"mdast":{"type":"root","children":[{"type":"block","children":[{"type":"paragraph","position":{"start":{"line":7,"column":1},"end":{"line":7,"column":1}},"children":[{"type":"emphasis","position":{"start":{"line":7,"column":1},"end":{"line":7,"column":1}},"children":[{"type":"text","value":"A difficult duty","position":{"start":{"line":7,"column":1},"end":{"line":7,"column":1}},"key":"spE5mDu1wm"}],"key":"nnfjxHhhhc"}],"key":"LNflvnnD0Z"},{"type":"thematicBreak","position":{"start":{"line":9,"column":1},"end":{"line":9,"column":1}},"key":"R7xENN8KNG"},{"type":"paragraph","position":{"start":{"line":11,"column":1},"end":{"line":11,"column":1}},"children":[{"type":"strong","position":{"start":{"line":11,"column":1},"end":{"line":11,"column":1}},"children":[{"type":"text","value":"This prayer is waiting to be written.","position":{"start":{"line":11,"column":1},"end":{"line":11,"column":1}},"key":"zvE3rMyCOw"}],"key":"SVaEIFpaxw"}],"key":"HgWQdpqZ1k"},{"type":"paragraph","position":{"start":{"line":13,"column":1},"end":{"line":13,"column":1}},"children":[{"type":"text","value":"Would you like to contribute? ","position":{"start":{"line":13,"column":1},"end":{"line":13,"column":1}},"key":"hvrXEtj4hZ"},{"type":"link","url":"https://github.com/yourusername/csprayers.com/edit/main/prayers/struggle/ethical/reporting-dishonesty.md","position":{"start":{"line":13,"column":1},"end":{"line":13,"column":1}},"children":[{"type":"text","value":"Submit a pull request","position":{"start":{"line":13,"column":1},"end":{"line":13,"column":1}},"key":"H0P7q2PSwR"}],"urlSource":"https://github.com/yourusername/csprayers.com/edit/main/prayers/struggle/ethical/reporting-dishonesty.md","error":true,"key":"ggSypWJWOj"},{"type":"text","value":" to add your prayer here.","position":{"start":{"line":13,"column":1},"end":{"line":13,"column":1}},"key":"lvLSTyMcaL"}],"key":"q0AKxfIxYg"}],"key":"YTgTlSHNUj"}],"key":"YhmpN2G0ac"},"references":{"cite":{"order":[],"data":{}}}}