{"version":2,"kind":"Article","sha256":"bc6275b62c1ff1a56515a56bb4f0cc1de0dd243012246ed066af0b2f201b83ab","slug":"student-discovers-calling","location":"/prayers/relationships/with-students/student-discovers-calling.md","dependencies":[],"frontmatter":{"title":"Watching a student discover their calling","content_includes_title":false,"authors":[{"nameParsed":{"literal":"CS Prayers Community","given":"CS Prayers","family":"Community"},"name":"CS Prayers Community","id":"contributors-myst-generated-uid-0"}],"github":"https://github.com/csprayers/csprayers.com","keywords":["prayer","computer science","education","faith"],"numbering":{"title":{"offset":2}},"source_url":"https://github.com/csprayers/csprayers.com/blob/main/prayers/relationships/with-students/student-discovers-calling.md","edit_url":"https://github.com/csprayers/csprayers.com/edit/main/prayers/relationships/with-students/student-discovers-calling.md","exports":[{"format":"md","filename":"student-discovers-calling.md","url":"/student-discovers-ca-62a54bd6657fba17659612916b5f0f1d.md"}]},"mdast":{"type":"root","children":[{"type":"block","children":[{"type":"paragraph","position":{"start":{"line":7,"column":1},"end":{"line":7,"column":1}},"children":[{"type":"emphasis","position":{"start":{"line":7,"column":1},"end":{"line":7,"column":1}},"children":[{"type":"text","value":"Joy of witnessing growth","position":{"start":{"line":7,"column":1},"end":{"line":7,"column":1}},"key":"PoMCetMYrL"}],"key":"YQeR3spWCf"}],"key":"G2eiCPNaNN"},{"type":"thematicBreak","position":{"start":{"line":9,"column":1},"end":{"line":9,"column":1}},"key":"qCM5orM1rG"},{"type":"paragraph","position":{"start":{"line":11,"column":1},"end":{"line":11,"column":1}},"children":[{"type":"strong","position":{"start":{"line":11,"column":1},"end":{"line":11,"column":1}},"children":[{"type":"text","value":"This prayer is waiting to be written.","position":{"start":{"line":11,"column":1},"end":{"line":11,"column":1}},"key":"mmzRipztTe"}],"key":"EwhdJP2UpJ"}],"key":"PBWJngcIVY"},{"type":"paragraph","position":{"start":{"line":13,"column":1},"end":{"line":13,"column":1}},"children":[{"type":"text","value":"Would you like to contribute? ","position":{"start":{"line":13,"column":1},"end":{"line":13,"column":1}},"key":"pFKHH3jqht"},{"type":"link","url":"https://github.com/yourusername/csprayers.com/edit/main/prayers/relationships/with-students/student-discovers-calling.md","position":{"start":{"line":13,"column":1},"end":{"line":13,"column":1}},"children":[{"type":"text","value":"Submit a pull request","position":{"start":{"line":13,"column":1},"end":{"line":13,"column":1}},"key":"SjT9H7VXnV"}],"urlSource":"https://github.com/yourusername/csprayers.com/edit/main/prayers/relationships/with-students/student-discovers-calling.md","error":true,"key":"FQ5mhQe6st"},{"type":"text","value":" to add your prayer here.","position":{"start":{"line":13,"column":1},"end":{"line":13,"column":1}},"key":"tKsV4JWz57"}],"key":"TqMcvvfqJf"}],"key":"W39zw7cHIP"}],"key":"tuyKCA3JGo"},"references":{"cite":{"order":[],"data":{}}}}